net2cog/__init__.py
net2cog/netcdf_convert.py
net2cog/netcdf_convert_harmony.py
net2cog/utilities.py
net2cog/validate_cloud_optimized_geotiff.py
net2cog-1.1.0.dist-info/LICENSE
net2cog-1.1.0.dist-info/METADATA
net2cog-1.1.0.dist-info/WHEEL
net2cog-1.1.0.dist-info/entry_points.txt
net2cog-1.1.0.dist-info/RECORD
